email_template_review_mcp/__init__.py
email_template_review_mcp/__main__.py
email_template_review_mcp/client.py
email_template_review_mcp/review_rules.py
email_template_review_mcp/server.py
email_template_review_mcp-1.1.1.dist-info/licenses/LICENSE
email_template_review_mcp-1.1.1.dist-info/METADATA
email_template_review_mcp-1.1.1.dist-info/WHEEL
email_template_review_mcp-1.1.1.dist-info/entry_points.txt
email_template_review_mcp-1.1.1.dist-info/top_level.txt
email_template_review_mcp-1.1.1.dist-info/RECORD
