Metadata-Version: 2.4
Name: email-template-review-mcp
Version: 1.1.1
Summary: MCP Server for automated email template review and management
Home-page: https://github.com/example/email-template-review-mcp
Author: Email Template Review Team
Author-email: admin@example.com
License: MIT
Requires-Python: >=3.8
License-File: LICENSE
Requires-Dist: mcp>=1.0.0
Requires-Dist: requests>=2.28.0
Requires-Dist: pydantic>=2.0.0
Provides-Extra: dev
Requires-Dist: pytest>=7.0.0; extra == "dev"
Requires-Dist: pytest-asyncio>=0.21.0; extra == "dev"
Requires-Dist: black>=23.0.0; extra == "dev"
Requires-Dist: mypy>=1.0.0; extra == "dev"
Dynamic: author-email
Dynamic: home-page
Dynamic: license-file
Dynamic: requires-python
